release_auditor/__init__.py
release_auditor/cli.py
release_auditor/utils.py
release_auditor-0.1.0.dist-info/LICENSE
release_auditor-0.1.0.dist-info/METADATA
release_auditor-0.1.0.dist-info/WHEEL
release_auditor-0.1.0.dist-info/entry_points.txt
release_auditor-0.1.0.dist-info/top_level.txt
release_auditor-0.1.0.dist-info/RECORD
