Metadata-Version: 2.1
Name: release-auditor
Version: 0.1.0
Summary: A tool for checking if release assets were modified after publication.
Home-page: https://github.com/nightwatchcybersecurity/release_auditor
Author: Nightwatch Cybersecurity
Author-email: research@nightwatchcybersecurity.com
License: Apache
Project-URL: Bug Reports, https://github.com/nightwatchcybersecurity/release_auditor/issues
Project-URL: Source, https://github.com/nightwatchcybersecurity/release_auditor
Platform: UNKNOWN
Classifier: Environment :: Console
Classifier: Development Status :: 3 - Alpha
Classifier: License :: OSI Approved :: Apache Software License
Classifier: Operating System :: OS Independent
Classifier: Programming Language :: Python :: 3.6
Classifier: Programming Language :: Python :: 3.7
Classifier: Programming Language :: Python :: 3.8
Classifier: Programming Language :: Python :: 3.9
Requires-Python: >=3.6
Requires-Dist: click (>=7.1.2)
Requires-Dist: PyGithub (>=1.54)
Requires-Dist: python-dateutil (>=1.4)
Requires-Dist: pytest (>=6.2.3)
Requires-Dist: pytest-cov (>=2.11.1)
